kapito/__init__.py
kapito/cli.py
kapito/logger.py
kapito/main.py
kapito/rules/__init__.py
kapito/rules/captcha.py
kapito/rules/cdn.py
kapito/rules/cms.py
kapito/rules/media.py
kapito/rules/waf.py
kapito/utils.py
kapito-0.3.0.dist-info/METADATA
kapito-0.3.0.dist-info/WHEEL
kapito-0.3.0.dist-info/entry_points.txt
kapito-0.3.0.dist-info/RECORD
