Metadata-Version: 2.3
Name: kapito
Version: 0.3.0
Summary: A short description of the project.
Author: walidsa3d
Requires-Python: >=3.10,<4.0
Classifier: Programming Language :: Python :: 3
Classifier: Programming Language :: Python :: 3.10
Classifier: Programming Language :: Python :: 3.11
Classifier: Programming Language :: Python :: 3.12
Classifier: Programming Language :: Python :: 3.13
Requires-Dist: click (>=8.1.3,<9.0.0)
Requires-Dist: hrequests (>=0.8.2,<0.9.0)
Requires-Dist: lxml (>=5.3.0,<6.0.0)
Requires-Dist: parsel (>=1.9.1,<2.0.0)
Requires-Dist: requests (>=2.32.3,<3.0.0)
